ichingpy/__init__.py
ichingpy/divination/__init__.py
ichingpy/divination/base.py
ichingpy/divination/iching.py
ichingpy/divination/six_lines.py
ichingpy/enum/__init__.py
ichingpy/enum/branch.py
ichingpy/enum/five_phase.py
ichingpy/enum/language.py
ichingpy/enum/line_status.py
ichingpy/enum/mixed_enum.py
ichingpy/enum/palace.py
ichingpy/enum/six_relative.py
ichingpy/enum/stem.py
ichingpy/model/__init__.py
ichingpy/model/four_pillars.py
ichingpy/model/hexagram.py
ichingpy/model/line.py
ichingpy/model/sexagenary_cycle.py
ichingpy/model/trigram.py
ichingpy/model/interpretation/__init__.py
ichingpy/model/interpretation/base.py
ichingpy/model/interpretation/hexagram/__init__.py
ichingpy/model/interpretation/hexagram/base.py
ichingpy/model/interpretation/hexagram/iching_hexagram.py
ichingpy/model/interpretation/hexagram/six_line_hexagram.py
ichingpy/model/interpretation/line/__init__.py
ichingpy/model/interpretation/line/base.py
ichingpy/model/interpretation/line/iching_line.py
ichingpy/model/interpretation/line/six_line_line.py
ichingpy/model/interpretation/trigram/__init__.py
ichingpy/model/interpretation/trigram/base.py
ichingpy/model/interpretation/trigram/iching_trigram.py
ichingpy/model/interpretation/trigram/six_line_trigram.py
ichingpy-0.1.9.dist-info/LICENSE
ichingpy-0.1.9.dist-info/METADATA
ichingpy-0.1.9.dist-info/WHEEL
ichingpy-0.1.9.dist-info/top_level.txt
ichingpy-0.1.9.dist-info/RECORD
