Metadata-Version: 2.2
Name: ichingpy
Version: 0.1.9
Summary: I-Ching objects construction using Python type hints.
Author-email: Jinyang Wang <jinyang.wang27@outlook.com>
License: MIT
Project-URL: Homepage, https://github.com/JinyangWang27/ichingpy
Requires-Python: >=3.10
License-File: LICENSE
Requires-Dist: pydantic
Provides-Extra: dev
Requires-Dist: black; extra == "dev"
Requires-Dist: pytest; extra == "dev"
Requires-Dist: pytest-cov; extra == "dev"
Requires-Dist: ipykernel; extra == "dev"
Requires-Dist: rich; extra == "dev"
Requires-Dist: mkdocstrings; extra == "dev"
Requires-Dist: mkdocs-material; extra == "dev"
Requires-Dist: mkdocstrings-python; extra == "dev"
